km/__init__.py
km/main.py
km-0.1.5.dist-info/entry_points.txt
km-0.1.5.dist-info/WHEEL
km-0.1.5.dist-info/METADATA
km-0.1.5.dist-info/RECORD
