Metadata-Version: 2.1
Name: km
Version: 0.1.5
Summary: 
Author: Eyal Levin
Author-email: eyalev@gmail.com
Requires-Python: >=3.6,<4.0
Classifier: Programming Language :: Python :: 3
Classifier: Programming Language :: Python :: 3.6
Classifier: Programming Language :: Python :: 3.7
Classifier: Programming Language :: Python :: 3.8
Requires-Dist: click (>=7.1.1,<8.0.0)
Requires-Dist: diskcache (>=4.1.0,<5.0.0)
Requires-Dist: requests (>=2.23.0,<3.0.0)
Requires-Dist: validators (>=0.14.3,<0.15.0)
